aligntext/__init__.py
aligntext-1.0.3.dist-info/LICENSE
aligntext-1.0.3.dist-info/METADATA
aligntext-1.0.3.dist-info/WHEEL
aligntext-1.0.3.dist-info/RECORD
